dweeter/__init__.py
dweeter/dweeter.py
dweeter-0.3.0.dist-info/LICENSE
dweeter-0.3.0.dist-info/METADATA
dweeter-0.3.0.dist-info/WHEEL
dweeter-0.3.0.dist-info/top_level.txt
dweeter-0.3.0.dist-info/RECORD
