Metadata-Version: 2.1
Name: dweeter
Version: 0.3.0
Summary: Encrypted messaging through the free dweet service.
Author-email: Quan Lin <jacklinquan@gmail.com>
License: MIT License
Project-URL: Homepage, https://github.com/jacklinquan/dweeter
Keywords: dweet
Classifier: License :: OSI Approved :: MIT License
Classifier: Programming Language :: Python
Classifier: Programming Language :: Python :: 3
Requires-Python: >=3.7
License-File: LICENSE
Requires-Dist: basicdweet
Requires-Dist: cryptomsg
Provides-Extra: aiohttp
Requires-Dist: aiohttp ; extra == 'aiohttp'
Provides-Extra: dev
Requires-Dist: aiohttp ; extra == 'dev'
Requires-Dist: black ; extra == 'dev'
Requires-Dist: pytest ; extra == 'dev'
